Workbook

Sheet relatório_transacoes
A1: Pedidos dessa entrega | B1: Data Pedido | C1: Cliente | D1: Telefone | E1: Email | F1: Documento | G1: Entrega | H1: Fatur.(R$) | I1: Pgto. | J1: Parcelas | K1: Máquina de cartão | L1: CV | M1: Cidade | N1: UF | O1: Status | P1: Data Reembolso | Q1: Comissão de Total de Usuários | R1: Taxa de Transação Total | S1: Operador | T1: Comis. Op | U1: Taxa de Máq. | V1: Taxa Ent. | W1: Entregador | X1: Quilometragem | Y1: Comis. Entregador (R$) | Z1: Lucro | AA1: Histórico | AB1: OPERAÇÃO | AC1: DATA ENTREGA
A2: ordezz02x | B2: 2025-12-23 19:00:18 | C2: Antônio Augusto de Oliveira | D2: (47) 98824-2871 | F2: 816.996.386-91 | G2: 2026-01-05 18:39:30 | H2: 159.9 | I2: Pix | M2: Barra Velha | N2: SC | O2: Completo | S2: Matheus Navegantes | W2: Bruno Farias pereira | AB2: GRANDE NAVEGANTES | AC2: 05/01/2026
A3: ord5oo1yr | B3: 2025-12-23 19:43:54 | C3: Gerson Rodrigues de Oliveira | D3: (61) 99128-1339 | F3: 444.448.501-91 | G3: 2026-01-05 16:54:06 | H3: 397 | I3: Cartão de Crédito | M3: Guará | N3: DF | O3: Completo | S3: Adriel Goiânia | W3: Leonardo Cunha lima | AB3: GRANDE GOIÂNIA | AC3: 05/01/2026
A4: ordxkkq2r | B4: 2025-12-23 21:12:21 | C4: Gislene Aparecida de Morais | D4: (37) 98834-6696 | F4: 021.320.557-26 | G4: 2026-01-05 13:45:48 | H4: 150 | I4: Dinheiro | M4: Divinópolis | N4: MG | O4: Completo | S4: Tiago Belo horizonte | W4: Lucimar José martins | AB4: GRANDE BELO HORIZONTE | AC4: 05/01/2026
A5: ordjxxoly | B5: 2025-12-24 11:14:03 | C5: Angela Maria Camargos | D5: (37) 99116-3782 | F5: 811.201.171-00 | G5: 2026-01-05 09:09:32 | H5: 150 | I5: PIX | M5: Nova Serrana | N5: MG | O5: Completo | S5: Tiago Belo horizonte | W5: Lucimar José martins | AB5: GRANDE BELO HORIZONTE | AC5: 05/01/2026
A6: ordqggvql | B6: 2025-12-24 15:06:22 | C6: Emily Rose vitoriano de | D6: (11) 95890-0544 | F6: 213.550.128-05 | G6: 2026-01-05 15:52:07 | H6: 197 | I6: Dinheiro | M6: Praia Grande | N6: SP | O6: Completo | S6: Alan São paulo | W6: Mateus Brasil silva | AB6: GRANDE SÃO PAULO | AC6: 05/01/2026
A7: ord6yyzk0 | B7: 2025-12-24 17:08:43 | C7: Iris Murta | D7: (37) 98418-6575 | F7: 485.307.368-00 | G7: 2026-01-05 15:12:16 | H7: 150 | I7: Dinheiro | M7: Divinópolis | N7: MG | O7: Completo | S7: Tiago Belo horizonte | W7: Bruno Martins | AB7: GRANDE BELO HORIZONTE | AC7: 05/01/2026
A8: ordvqqzlm | B8: 2025-12-24 17:10:43 | C8: CREUZA MARIA ONEZIO | D8: (31) 99303-8539 | F8: 460.011.188-50 | G8: 2026-01-07 17:51:22 | H8: 147 | I8: Cartão de Débito | M8: Juatuba | N8: MG | O8: Completo | S8: Tiago Belo horizonte | W8: Lucimar José martins | AB8: GRANDE BELO HORIZONTE | AC8: 07/01/2026
A9: ordn99jrn | B9: 2025-12-25 07:21:44 | C9: Inês domingos da Silva Gomes | D9: (13) 98832-5682 | F9: 295.376.338-45 | G9: 2026-01-05 16:47:34 | H9: 197 | I9: Cartão de Crédito | M9: Santos | N9: SP | O9: Completo | S9: Alan São paulo | W9: Julio Cesar lima de souza | AB9: GRANDE SÃO PAULO | AC9: 05/01/2026
A10: ord2ggl56 | B10: 2025-12-25 09:54:23 | C10: Eula . 02 | D10: (27) 99225-1478 | F10: 111.824.114-28 | G10: 2026-01-05 17:54:09 | H10: 197.9 | I10: Dinheiro | M10: Serra | N10: ES | O10: Completo | S10: João Vitória | W10: Marciney' Oscar bueker de freitas | AB10: GRANDE VITÓRIA | AC10: 05/01/2026
A11: ordvqq5ym | B11: 2025-12-25 12:37:25 | C11: Sílvia Marlian Campregher | D11: (47) 99102-3520 | F11: 199.294.878-08 | G11: 2026-01-05 19:54:05 | H11: 217 | I11: PIX | M11: Jaraguá do Sul | N11: SC | O11: Completo | S11: Matheus Navegantes | W11: Bruno Augustinho matias | AB11: GRANDE NAVEGANTES | AC11: 05/01/2026
A12: ordm22qk6 | B12: 2025-12-25 13:09:24 | C12: Sílvia marlian Campregher | D12: (47) 99102-3520 | F12: 130.050.127-86 | G12: 2026-01-05 19:53:28 | H12: 150 | I12: PIX | M12: Jaraguá do Sul | N12: SC | O12: Completo | S12: Matheus Navegantes | W12: Bruno Augustinho matias | AB12: GRANDE NAVEGANTES | AC12: 05/01/2026
A13: ord7oogor | B13: 2025-12-25 14:42:33 | C13: Fátima . | D13: (37) 99945-7413 | F13: 811.843.446-04 | G13: 2026-01-05 15:07:24 | H13: 147 | I13: Dinheiro | M13: Divinópolis | N13: MG | O13: Completo | S13: Tiago Belo horizonte | W13: Bruno Martins | AB13: GRANDE BELO HORIZONTE | AC13: 05/01/2026
... A4323: ord2gnxx6 | B4323: 2026-01-07 14:59:23 | C4323: JOSEFA MOREIRA DA SILVA BARROSO | D4323: (62) 98552-9457 | F4323: 931.055.923-34 | G4323: 2026-01-07 18:35:21 | H4323: 297 | I4323: Cartão de Crédito | M4323: Goiânia | N4323: GO | O4323: Completo | S4323: Adriel Goiânia | W4323: Miguel Arcanjo nogueira junior | AB4323: GRANDE GOIÂNIA | AC4323: 07/01/2026
A4324: orddxxnmm | B4324: 2025-12-27 10:17:09 | C4324: OSNI PASSOS | D4324: (41) 99998-2343 | F4324: 768.908.482-68 | G4324: 2026-01-09 09:46:15 | H4324: 99.9 | I4324: PIX | M4324: Piraquara | N4324: PR | O4324: Completo | S4324: Gidalto Curitiba | W4324: Maicon Wiliam lemes | AB4324: GRANDE CURITIBA | AC4324: =TEXT(G4324,"dd/mm/aaaa") -> 09/01/2026
A4325: ordjxxrkv | B4325: 2025-12-27 11:30:28 | C4325: Paulo Cesar dos Santos | D4325: (13) 98876-0612 | F4325: 040.970.050-90 | G4325: 2026-01-09 17:39:43 | H4325: 149.9 | I4325: PIX | M4325: Santos | N4325: SP | O4325: Completo | S4325: Alan São paulo | W4325: Mateus Brasil silva | AB4325: GRANDE SÃO PAULO | AC4325: =TEXT(G4325,"dd/mm/aaaa") -> 09/01/2026
A4326: ord39q03o | B4326: 2025-12-28 21:10:44 | C4326: Tatiana Dobrev | D4326: (12) 98897-9018 | F4326: 185.455.338-02 | G4326: 2026-01-10 16:25:02 | H4326: 149 | I4326: PIX | M4326: São José dos Campos | N4326: SP | O4326: Completo | S4326: Alan São paulo | W4326: Joao Vitor ferraz santos | AB4326: GRANDE SÃO PAULO | AC4326: =TEXT(G4326,"dd/mm/aaaa") -> 10/01/2026
A4327: ord6y11n1 | B4327: 2025-12-29 14:42:17 | C4327: Cristiane Batista Cardeal | D4327: (12) 97401-0704 | F4327: 071.604.047-69 | G4327: 2026-01-10 14:42:41 | H4327: 150 | I4327: PIX | M4327: São José dos Campos | N4327: SP | O4327: Completo | S4327: Alan São paulo | W4327: Joao Vitor ferraz santos | AB4327: GRANDE SÃO PAULO | AC4327: =TEXT(G4327,"dd/mm/aaaa") -> 10/01/2026
A4328: ord7o6myv | B4328: 2025-12-29 16:09:00 | C4328: zenaide Lopes Teixeira | D4328: (12) 97253-3551 | F4328: 225.739.198-54 | G4328: 2026-01-10 16:10:14 | H4328: 297 | I4328: Cartão de Débito | M4328: São José dos Campos | N4328: SP | O4328: Completo | S4328: Alan São paulo | W4328: Joao Vitor ferraz santos | AB4328: GRANDE SÃO PAULO | AC4328: =TEXT(G4328,"dd/mm/aaaa") -> 10/01/2026
A4329: ordk23p1l | B4329: 2025-12-29 16:12:11 | C4329: Maione Gomes dos Santos | D4329: (37) 99985-2054 | F4329: 102.797.896-70 | G4329: 2026-01-08 08:48:02 | H4329: 197 | I4329: Cartão de Débito | M4329: Nova Serrana | N4329: MG | O4329: Completo | S4329: Tiago Belo horizonte | W4329: Lucimar José martins | AB4329: GRANDE BELO HORIZONTE | AC4329: =TEXT(G4329,"dd/mm/aaaa") -> 08/01/2026
A4330: ordvqp2j3 | B4330: 2025-12-29 16:28:40 | C4330: Maria Helena da Silva | D4330: (12) 99647-1826 | F4330: 101.414.068-44 | G4330: 2026-01-10 11:59:45 | H4330: 150 | I4330: Dinheiro | M4330: Taubaté | N4330: SP | O4330: Completo | S4330: Alan São paulo | W4330: Bruno Figueiredo pacini | AB4330: GRANDE SÃO PAULO | AC4330: =TEXT(G4330,"dd/mm/aaaa") -> 10/01/2026
A4331: ord2gz1v6/ordy7qrmv | B4331: 2025-12-29 20:02:44 | C4331: Andreia da silva | D4331: (11) 99941-2250 | F4331: 170.692.698-70 | G4331: 2026-01-09 13:08:51 | H4331: 137 | I4331: PIX | M4331: Franco da Rocha | N4331: SP | O4331: Completo | S4331: Alan São paulo | W4331: Leonardo Andrade nascimento antônio | AB4331: GRANDE SÃO PAULO | AC4331: =TEXT(G4331,"dd/mm/aaaa") -> 09/01/2026
A4332: ord2gzymz | B4332: 2025-12-30 11:16:14 | C4332: Iolanda Oliveira Ferreira da Silva | D4332: (12) 98895-0082 | F4332: 769.068.333-91 | G4332: 2026-01-10 16:30:19 | H4332: 297 | I4332: Cartão de Crédito | M4332: Jacareí | N4332: SP | O4332: Completo | S4332: Alan São paulo | W4332: Bruno Figueiredo pacini | AB4332: GRANDE SÃO PAULO | AC4332: =TEXT(G4332,"dd/mm/aaaa") -> 10/01/2026
A4333: ord9p90ev | B4333: 2025-12-30 11:34:11 | C4333: Edinalda da Conceição | D4333: (61) 99315-2600 | F4333: 027.464.591-24 | G4333: 2026-01-10 15:28:04 | H4333: 297 | I4333: Cartão de Crédito | M4333: Águas Lindas de Goiás | N4333: GO | O4333: Completo | S4333: Adriel Goiânia | W4333: Daniel Tiago das merces silva | AB4333: GRANDE GOIÂNIA | AC4333: =TEXT(G4333,"dd/mm/aaaa") -> 10/01/2026
A4334: ord5ok20r | B4334: 2025-12-30 12:33:48 | C4334: Nilma Santana | D4334: (47) 99720-0821 | F4334: 036.999.061-75 | G4334: 2026-01-10 13:52:03 | H4334: 119.9 | I4334: Cartão de Débito | M4334: Blumenau | N4334: SC | O4334: Completo | S4334: Matheus Navegantes | W4334: Bruno Farias pereira | AB4334: GRANDE NAVEGANTES | AC4334: =TEXT(G4334,"dd/mm/aaaa") -> 10/01/2026
A4335: ordgd25ev | B4335: 2025-12-30 12:35:16 | C4335: Cileia Santos Carvalho | D4335: (11) 99321-6341 | F4335: 258.054.428-33 | G4335: 2026-01-10 15:07:03 | H4335: 397 | I4335: Dinheiro | M4335: São José dos Campos | N4335: SP | O4335: Completo | S4335: Alan São paulo | W4335: Joao Vitor ferraz santos | AB4335: GRANDE SÃO PAULO | AC4335: =TEXT(G4335,"dd/mm/aaaa") -> 10/01/2026
... A8113: orddxen0k | B8113: 2026-01-10 11:20:34 | C8113: Léa De Oliveira Martins | D8113: (61) 99998-8415 | F8113: 454.590.456-49 | G8113: 2026-01-10 13:13:30 | H8113: 137 | I8113: Cartão de Débito | M8113: Aparecida de Goiânia | N8113: GO | O8113: Completo | S8113: Adriel Goiânia | W8113: Miguel Arcanjo nogueira junior | AB8113: GRANDE GOIÂNIA | AC8113: =TEXT(G8113,"dd/mm/aaaa") -> 10/01/2026
A8114: ord07pl0 | B8114: 2024-10-02 21:59:15 | C8114: Marinalva P Nunes | D8114: (92) 98158-6696 | F8114: 535.388.032-34 | G8114: 2026-01-12 11:18:07 | H8114: 150 | I8114: PIX | M8114: Manaus | N8114: AM | O8114: Completo | S8114: Giselle Manaus | W8114: Lilian Monteiro dos santos | AB8114: =_xlfn.XLOOKUP(S8114,contatos_gerentes!D:D,contatos_gerentes!B:B) -> GRANDE MANAUS | AC8114: =TEXT(G8114,"dd/mm/aaaa") -> 12/01/2026
A8115: ord2gze7z | B8115: 2025-12-30 21:48:05 | C8115: Alvaci Teresinha | D8115: (51) 99552-5895 | F8115: 441.355.408-64 | G8115: 2026-01-12 16:51:28 | H8115: 119.9 | I8115: Dinheiro | M8115: Guaíba | N8115: RS | O8115: Completo | S8115: Darlan Porto alegre | W8115: Luiz Felipe valin caetano | AB8115: =_xlfn.XLOOKUP(S8115,contatos_gerentes!D:D,contatos_gerentes!B:B) -> GRANDE PORTO ALEGRE | AC8115: =TEXT(G8115,"dd/mm/aaaa") -> 12/01/2026
A8116: ordz7d2x7 | B8116: 2025-12-31 13:46:31 | C8116: João Natanael Dornelles da Fontoura | D8116: (47) 99175-7172 | F8116: 882.347.030-72 | G8116: 2026-01-12 14:11:41 | H8116: 198.01 | I8116: Cartão de Débito | M8116: Barra Velha | N8116: SC | O8116: Completo | S8116: Matheus Navegantes | W8116: Bruno Augustinho matias | AB8116: GRANDE NAVEGANTES | AC8116: =TEXT(G8116,"dd/mm/aaaa") -> 12/01/2026
A8117: ordrjmemv | B8117: 2026-01-01 16:30:15 | C8117: Maria Rosa Nunes Alves | D8117: (51) 99679-4506 | F8117: 456.913.800-44 | G8117: 2026-01-12 16:52:51 | H8117: 129.99 | I8117: Dinheiro | M8117: Guaíba | N8117: RS | O8117: Completo | S8117: Darlan Porto alegre | W8117: Luiz Felipe valin caetano | AB8117: =_xlfn.XLOOKUP(S8117,contatos_gerentes!D:D,contatos_gerentes!B:B) -> GRANDE PORTO ALEGRE | AC8117: =TEXT(G8117,"dd/mm/aaaa") -> 12/01/2026
A8118: ordp9m13m | B8118: 2026-01-02 19:35:19 | C8118: MARCIA ELISA | D8118: (54) 99711-4696 | F8118: 022.066.018-26 | G8118: 2026-01-12 12:22:38 | H8118: 109.99 | I8118: Dinheiro | M8118: Bento Gonçalves | N8118: RS | O8118: Completo | S8118: Darlan Porto alegre | W8118: Leomar Horbach vieira | AB8118: =_xlfn.XLOOKUP(S8118,contatos_gerentes!D:D,contatos_gerentes!B:B) -> GRANDE PORTO ALEGRE | AC8118: =TEXT(G8118,"dd/mm/aaaa") -> 12/01/2026
A8119: orddx2k3o | B8119: 2026-01-02 21:18:36 | C8119: vilmar borba | D8119: (47) 99207-8915 | F8119: 017.629.589-53 | G8119: 2026-01-13 19:44:54 | H8119: 197 | I8119: Dinheiro | M8119: Joinville | N8119: SC | O8119: Completo | S8119: Matheus Navegantes | W8119: Bruno Augustinho matias | AB8119: GRANDE NAVEGANTES | AC8119: =TEXT(G8119,"dd/mm/aaaa") -> 13/01/2026
A8120: ord0lkrx0 | B8120: 2026-01-03 08:18:22 | C8120: CLAUDETE PASSAIA | D8120: (54) 99952-3720 | F8120: 674.588.740-15 | G8120: 2026-01-12 10:51:06 | H8120: 197 | I8120: Cartão de Crédito | M8120: Bento Gonçalves | N8120: RS | O8120: Completo | S8120: Darlan Porto alegre | W8120: Leomar Horbach vieira | AB8120: =_xlfn.XLOOKUP(S8120,contatos_gerentes!D:D,contatos_gerentes!B:B) -> GRANDE PORTO ALEGRE | AC8120: =TEXT(G8120,"dd/mm/aaaa") -> 12/01/2026
A8121: ord5okq05 | B8121: 2026-01-03 15:20:07 | C8121: Chirlei Helena da Silva | D8121: (37) 99802-3028 | F8121: 858.548.756-91 | G8121: 2026-01-12 11:15:03 | H8121: 197 | I8121: PIX | M8121: Divinópolis | N8121: MG | O8121: Completo | S8121: Tiago Belo horizonte | W8121: Lucimar José martins | AB8121: =_xlfn.XLOOKUP(S8121,contatos_gerentes!D:D,contatos_gerentes!B:B) -> GRANDE BELO HORIZONTE | AC8121: =TEXT(G8121,"dd/mm/aaaa") -> 12/01/2026
A8122: ord1g1lem | B8122: 2026-01-04 07:58:27 | C8122: Cristina Guimarães Santos de Jesus | D8122: (11) 99141-6082 | F8122: 288.005.058-80 | G8122: 2026-01-12 12:59:45 | H8122: 197 | I8122: Dinheiro | M8122: Jundiaí | N8122: SP | O8122: Completo | S8122: Alan São paulo | W8122: Maicon Da silva rocha | AB8122: =_xlfn.XLOOKUP(S8122,contatos_gerentes!D:D,contatos_gerentes!B:B) -> GRANDE SÃO PAULO | AC8122: =TEXT(G8122,"dd/mm/aaaa") -> 12/01/2026
A8123: ordo62mng | B8123: 2026-01-04 10:01:25 | C8123: Dioclesio Marcos | D8123: (47) 99692-3389 | F8123: 021.897.993-25 | G8123: 2026-01-13 12:32:53 | H8123: 217 | I8123: Dinheiro | M8123: Joinville | N8123: SC | O8123: Completo | S8123: Matheus Navegantes | W8123: Bruno Augustinho matias | AB8123: GRANDE NAVEGANTES | AC8123: =TEXT(G8123,"dd/mm/aaaa") -> 13/01/2026
A8124: ordp9mrye | B8124: 2026-01-04 13:26:47 | C8124: JOSE HURTADO | D8124: (95) 98413-9865 | F8124: 348.521.906-15 | G8124: 2026-01-13 14:53:22 | H8124: 100 | I8124: PIX | M8124: Joinville | N8124: SC | O8124: Completo | S8124: Matheus Navegantes | W8124: Bruno Augustinho matias | AB8124: GRANDE NAVEGANTES | AC8124: =TEXT(G8124,"dd/mm/aaaa") -> 13/01/2026
A8125: ordy7ql2j | B8125: 2026-01-04 20:38:51 | C8125: Anderson Ferreira de Lima | D8125: (12) 98892-3974 | F8125: 298.804.158-09 | G8125: 2026-01-13 12:08:03 | H8125: 169.9 | I8125: Dinheiro | M8125: Jacareí | N8125: SP | O8125: Completo | S8125: Alan São paulo | W8125: Felipe alexandre De souza | AB8125: =_xlfn.XLOOKUP(S8125,contatos_gerentes!D:D,contatos_gerentes!B:B) -> GRANDE SÃO PAULO | AC8125: =TEXT(G8125,"dd/mm/aaaa") -> 13/01/2026
A8126: ordy7qlp3 | B8126: 2026-01-05 00:01:54 | C8126: Derivaldo santos | D8126: (12) 98155-9083 | F8126: 051.491.805-56 | G8126: 2026-01-13 13:08:16 | H8126: 249.9 | I8126: Cartão de Débito | M8126: Jacareí | N8126: SP | O8126: Completo | S8126: Alan São paulo | W8126: Felipe alexandre De souza | AB8126: =_xlfn.XLOOKUP(S8126,contatos_gerentes!D:D,contatos_gerentes!B:B) -> GRANDE SÃO PAULO | AC8126: =TEXT(G8126,"dd/mm/aaaa") -> 13/01/2026
A8127: ordrjyxxm | B8127: 2026-01-05 07:55:47 | C8127: Mateus Alves Ribeiro | D8127: (41) 99680-5830 | F8127: 861.228.000-15 | G8127: 2026-01-12 12:52:36 | H8127: 100 | I8127: Dinheiro | M8127: Campo Largo | N8127: PR | O8127: Completo | S8127: Gidalto Curitiba | W8127: João Paulo de lima | AB8127: =_xlfn.XLOOKUP(S8127,contatos_gerentes!D:D,contatos_gerentes!B:B) -> GRANDE CURITIBA | AC8127: =TEXT(G8127,"dd/mm/aaaa") -> 12/01/2026
A8128: ord2gnd1z | B8128: 2026-01-05 09:19:27 | C8128: paulo matias fortunato | D8128: (47) 99937-3550 | F8128: 532.509.159-04 | G8128: 2026-01-13 16:20:21 | H8128: 697 | I8128: Dinheiro | M8128: Joinville | N8128: SC | O8128: Completo | S8128: Matheus Navegantes | W8128: Bruno Augustinho matias | AB8128: GRANDE NAVEGANTES | AC8128: =TEXT(G8128,"dd/mm/aaaa") -> 13/01/2026
A8129: ordk2pqej | B8129: 2026-01-05 10:08:51 | C8129: Maria Madalena Delai Molinari | D8129: (47) 99642-8405 | F8129: 021.784.189-96 | G8129: 2026-01-13 14:19:59 | H8129: 197 | I8129: Cartão de crédito | M8129: Joinville | N8129: SC | O8129: Completo | S8129: Matheus Navegantes | W8129: Bruno Augustinho matias | AB8129: GRANDE NAVEGANTES | AC8129: =TEXT(G8129,"dd/mm/aaaa") -> 13/01/2026
A8130: ordz7lro5 | B8130: 2026-01-05 10:45:41 | C8130: ELIANE CLIENTE | D8130: (47) 99713-0313 | F8130: 091.997.877-09 | G8130: 2026-01-13 11:02:47 | H8130: 149.9 | I8130: Dinheiro | M8130: Joinville | N8130: SC | O8130: Completo | S8130: Matheus Navegantes | W8130: Bruno Augustinho matias | AB8130: GRANDE NAVEGANTES | AC8130: =TEXT(G8130,"dd/mm/aaaa") -> 13/01/2026
A8131: ord7ome3m | B8131: 2026-01-05 13:01:51 | C8131: Maria Esmeralda Martins | D8131: (37) 99911-6874 | F8131: 094.727.186-47 | G8131: 2026-01-12 09:13:11 | H8131: 139.99 | I8131: Dinheiro | M8131: Nova Serrana | N8131: MG | O8131: Completo | S8131: Tiago Belo horizonte | W8131: Lucimar José martins | AB8131: =_xlfn.XLOOKUP(S8131,contatos_gerentes!D:D,contatos_gerentes!B:B) -> GRANDE BELO HORIZONTE | AC8131: =TEXT(G8131,"dd/mm/aaaa") -> 12/01/2026
A8132: ord39ynxe | B8132: 2026-01-05 13:47:08 | C8132: daiane schmitt correa | D8132: (47) 99125-1513 | F8132: 038.309.860-25 | G8132: 2026-01-14 12:21:55 | H8132: 197 | I8132: PIX | M8132: Itapema | N8132: SC | O8132: Completo | S8132: Matheus Navegantes | W8132: Alisson Diogo matias | AB8132: GRANDE NAVEGANTES | AC8132: =TEXT(G8132,"dd/mm/aaaa") -> 14/01/2026
A8133: ordqgod36 | B8133: 2026-01-05 13:55:31 | C8133: MARIA GORET | D8133: (47) 99936-1762 | F8133: 007.113.016-03 | G8133: 2026-01-13 11:17:11 | H8133: 297 | I8133: Dinheiro | M8133: Joinville | N8133: SC | O8133: Completo | S8133: Matheus Navegantes | W8133: Bruno Augustinho matias | AB8133: GRANDE NAVEGANTES | AC8133: =TEXT(G8133,"dd/mm/aaaa") -> 13/01/2026
A8134: ordqgox5l | B8134: 2026-01-05 14:50:01 | C8134: Rodrigo Cezar da Silva | D8134: (47) 99972-7629 | F8134: 384.442.638-85 | G8134: 2026-01-13 17:41:14 | H8134: 124.99 | I8134: PIX | M8134: Joinville | N8134: SC | O8134: Completo | S8134: Matheus Navegantes | W8134: Bruno Augustinho matias | AB8134: GRANDE NAVEGANTES | AC8134: =TEXT(G8134,"dd/mm/aaaa") -> 13/01/2026
A8135: ordxk7px1 | B8135: 2026-01-05 15:14:14 | C8135: Clayton Souza Marques | D8135: (47) 99999-6683 | F8135: 332.784.538-75 | G8135: 2026-01-13 15:18:18 | H8135: 144.01 | I8135: Dinheiro | M8135: Joinville | N8135: SC | O8135: Completo | S8135: Matheus Navegantes | W8135: Bruno Augustinho matias | AB8135: GRANDE NAVEGANTES | AC8135: =TEXT(G8135,"dd/mm/aaaa") -> 13/01/2026
A8136: ordjx7m9x | B8136: 2026-01-05 16:37:35 | C8136: Neli Chagas da Rosa | D8136: (54) 99704-0040 | F8136: 032.602.790-40 | G8136: 2026-01-13 10:38:36 | H8136: 297 | I8136: Cartão de Crédito | M8136: Caxias do Sul | N8136: RS | O8136: Completo | S8136: Darlan Porto alegre | W8136: Leomar Horbach vieira | AB8136: =_xlfn.XLOOKUP(S8136,contatos_gerentes!D:D,contatos_gerentes!B:B) -> GRANDE PORTO ALEGRE | AC8136: =TEXT(G8136,"dd/mm/aaaa") -> 13/01/2026
A8137: ordgdpeqe/ordn9plj9 | B8137: 2026-01-05 18:46:13 | C8137: Zilda F | D8137: (12) 98899-4106 | F8137: 000.101.322-01 | G8137: 2026-01-13 11:13:34 | H8137: 167 | I8137: Cartão de Crédito | M8137: Jacareí | N8137: SP | O8137: Completo | S8137: Alan São paulo | W8137: Felipe alexandre De souza | AB8137: =_xlfn.XLOOKUP(S8137,contatos_gerentes!D:D,contatos_gerentes!B:B) -> GRANDE SÃO PAULO | AC8137: =TEXT(G8137,"dd/mm/aaaa") -> 13/01/2026
A8138: ordz7l797 | B8138: 2026-01-05 20:40:15 | C8138: Dayane Cristina Bernardino | D8138: (47) 99661-4338 | F8138: 068.116.689-46 | G8138: 2026-01-12 10:57:00 | H8138: 129.9 | I8138: Pix | M8138: Itajaí | N8138: SC | O8138: Completo | S8138: Matheus Navegantes | W8138: Alisson Diogo matias | AB8138: GRANDE NAVEGANTES | AC8138: =TEXT(G8138,"dd/mm/aaaa") -> 12/01/2026
A8139: ord9pmp1j | B8139: 2026-01-05 21:01:31 | C8139: IRACILDA DUTRA DOS SANTOS | D8139: (51) 99645-3426 | F8139: 777.133.386-91 | G8139: 2026-01-12 09:56:46 | H8139: 159.9 | I8139: Dinheiro | M8139: São Sebastião do Caí | N8139: RS | O8139: Completo | S8139: Darlan Porto alegre | W8139: Leomar Horbach vieira | AB8139: =_xlfn.XLOOKUP(S8139,contatos_gerentes!D:D,contatos_gerentes!B:B) -> GRANDE PORTO ALEGRE | AC8139: =TEXT(G8139,"dd/mm/aaaa") -> 12/01/2026
A8140: ord6yjyvl | B8140: 2026-01-05 22:28:31 | C8140: Maria Aparecida Nogueira Cardoso | D8140: (37) 98841-0504 | F8140: 304.188.598-09 | G8140: 2026-01-12 10:51:50 | H8140: 197 | I8140: Cartão de Crédito | M8140: Divinópolis | N8140: MG | O8140: Completo | S8140: Tiago Belo horizonte | W8140: Lucimar José martins | AB8140: =_xlfn.XLOOKUP(S8140,contatos_gerentes!D:D,contatos_gerentes!B:B) -> GRANDE BELO HORIZONTE | AC8140: =TEXT(G8140,"dd/mm/aaaa") -> 12/01/2026
A8141: ordgdp236 | B8141: 2026-01-06 08:14:05 | C8141: Kelly Cristina de Gouveia | D8141: (12) 99777-1962 | F8141: 289.247.278-42 | G8141: 2026-01-13 16:10:08 | H8141: 129.9 | I8141: PIX | M8141: São José dos Campos | N8141: SP | O8141: Completo | S8141: Alan São paulo | W8141: Felipe alexandre De souza | AB8141: =_xlfn.XLOOKUP(S8141,contatos_gerentes!D:D,contatos_gerentes!B:B) -> GRANDE SÃO PAULO | AC8141: =TEXT(G8141,"dd/mm/aaaa") -> 13/01/2026
A8142: ord2gnzg6 | B8142: 2026-01-06 09:21:45 | C8142: Claudio Souza de Jesus | D8142: (13) 99757-8170 | F8142: 020.381.910-18 | G8142: 2026-01-14 18:24:42 | H8142: 150 | I8142: Dinheiro | M8142: São Vicente | N8142: SP | O8142: Completo | S8142: Alan São paulo | W8142: Julio Cesar lima de souza | AB8142: =_xlfn.XLOOKUP(S8142,contatos_gerentes!D:D,contatos_gerentes!B:B) -> GRANDE SÃO PAULO | AC8142: =TEXT(G8142,"dd/mm/aaaa") -> 14/01/2026
A8143: ordo6oo6d | B8143: 2026-01-06 12:14:01 | C8143: SR EDER | D8143: (47) 99612-7526 | F8143: 668.323.302-00 | G8143: 2026-01-13 15:42:28 | H8143: 99.9 | I8143: Dinheiro | M8143: Joinville | N8143: SC | O8143: Completo | S8143: Matheus Navegantes | W8143: Bruno Augustinho matias | AB8143: GRANDE NAVEGANTES | AC8143: =TEXT(G8143,"dd/mm/aaaa") -> 13/01/2026
A8144: ord1gyyyg | B8144: 2026-01-06 12:25:54 | C8144: José Costa de Souza | D8144: (37) 98809-6030 | F8144: 774.386.126-00 | G8144: 2026-01-12 12:08:35 | H8144: 199.9 | I8144: Dinheiro | M8144: Divinópolis | N8144: MG | O8144: Completo | S8144: Tiago Belo horizonte | W8144: Lucimar José martins | AB8144: =_xlfn.XLOOKUP(S8144,contatos_gerentes!D:D,contatos_gerentes!B:B) -> GRANDE BELO HORIZONTE | AC8144: =TEXT(G8144,"dd/mm/aaaa") -> 12/01/2026
A8145: ord6yjjpv | B8145: 2026-01-06 12:40:50 | C8145: Edgelson Cordeiro de Siqueira | D8145: (11) 94530-5850 | F8145: 592.576.954-68 | G8145: 2026-01-12 15:32:30 | H8145: 97.9 | I8145: Dinheiro | M8145: São Paulo | N8145: SP | O8145: Completo | S8145: Alan São paulo | W8145: Paulo Henrique da silva camilo | AB8145: =_xlfn.XLOOKUP(S8145,contatos_gerentes!D:D,contatos_gerentes!B:B) -> GRANDE SÃO PAULO | AC8145: =TEXT(G8145,"dd/mm/aaaa") -> 12/01/2026
A8146: ord5oj77z/ordm27zz3 | B8146: 2026-01-06 15:11:58 | C8146: Maria Aparecida Ferreira Guimarães | D8146: (37) 99809-1285 | F8146: 048.923.364-32 | G8146: 2026-01-12 08:18:09 | H8146: 398.01 | I8146: Dinheiro | M8146: Pará de Minas | N8146: MG | O8146: Completo | S8146: Tiago Belo horizonte | W8146: Lucimar José martins | AB8146: =_xlfn.XLOOKUP(S8146,contatos_gerentes!D:D,contatos_gerentes!B:B) -> GRANDE BELO HORIZONTE | AC8146: =TEXT(G8146,"dd/mm/aaaa") -> 12/01/2026
A8147: ordy75rj1 | B8147: 2026-01-06 15:26:31 | C8147: Magdália Macedo do Nascimento | D8147: (61) 98240-0551 | F8147: 854.960.063-68 | G8147: 2026-01-13 10:48:11 | H8147: 137 | I8147: Cartão de Débito | M8147: Taguatinga | N8147: DF | O8147: Completo | S8147: Adriel Goiânia | W8147: Leonardo Cunha lima | AB8147: =_xlfn.XLOOKUP(S8147,contatos_gerentes!D:D,contatos_gerentes!B:B) -> GRANDE GOIÂNIA | AC8147: =TEXT(G8147,"dd/mm/aaaa") -> 13/01/2026
A8148: ordrjyrg6 | B8148: 2026-01-06 15:42:26 | C8148: Miquéias Pinto | D8148: (11) 97467-2040 | F8148: 056.392.908-11 | G8148: 2026-01-14 14:12:08 | H8148: 167 | I8148: Cartão de Débito | M8148: Arujá | N8148: SP | O8148: Completo | S8148: Alan São paulo | W8148: Alyson Aparecido nicolini | AB8148: =_xlfn.XLOOKUP(S8148,contatos_gerentes!D:D,contatos_gerentes!B:B) -> GRANDE SÃO PAULO | AC8148: =TEXT(G8148,"dd/mm/aaaa") -> 14/01/2026
A8149: ordqgo16r | B8149: 2026-01-06 16:48:58 | C8149: Maria da Penha | D8149: (31) 98819-0948 | F8149: 152.154.926-54 | G8149: 2026-01-12 13:33:34 | H8149: 150 | I8149: Cartão de Crédito | M8149: Ribeirão das Neves | N8149: MG | O8149: Completo | S8149: Tiago Belo horizonte | W8149: Natanael Peixoto da silva | AB8149: =_xlfn.XLOOKUP(S8149,contatos_gerentes!D:D,contatos_gerentes!B:B) -> GRANDE BELO HORIZONTE | AC8149: =TEXT(G8149,"dd/mm/aaaa") -> 12/01/2026
A8150: ord7ompqr | B8150: 2026-01-06 18:40:13 | C8150: Marizete lorandi dos Santos | D8150: (55) 54914-0144 | F8150: 084.931.421-66 | G8150: 2026-01-13 14:15:32 | H8150: 119.99 | I8150: PIX | M8150: Caxias do Sul | N8150: RS | O8150: Completo | S8150: Darlan Porto alegre | W8150: Luiz Felipe valin caetano | AB8150: =_xlfn.XLOOKUP(S8150,contatos_gerentes!D:D,contatos_gerentes!B:B) -> GRANDE PORTO ALEGRE | AC8150: =TEXT(G8150,"dd/mm/aaaa") -> 13/01/2026
A8151: ordk2p70l | B8151: 2026-01-06 21:06:30 | C8151: ANDREIA FONSECA FERREIRA | D8151: (54) 99246-3737 | F8151: 059.529.496-06 | G8151: 2026-01-13 16:03:41 | H8151: 119.9 | I8151: Dinheiro | M8151: Caxias do Sul | N8151: RS | O8151: Completo | S8151: Darlan Porto alegre | W8151: Luiz Felipe valin caetano | AB8151: =_xlfn.XLOOKUP(S8151,contatos_gerentes!D:D,contatos_gerentes!B:B) -> GRANDE PORTO ALEGRE | AC8151: =TEXT(G8151,"dd/mm/aaaa") -> 13/01/2026
A8152: ordjx73g1 | B8152: 2026-01-06 22:10:51 | C8152: Maria Aparecida Roriz de Oliveira | D8152: (61) 98518-2782 | F8152: 120.326.891-20 | G8152: 2026-01-13 09:18:51 | H8152: 129.99 | I8152: PIX | M8152: Ceilândia | N8152: DF | O8152: Completo | S8152: Adriel Goiânia | W8152: Daniel Tiago das merces silva | AB8152: =_xlfn.XLOOKUP(S8152,contatos_gerentes!D:D,contatos_gerentes!B:B) -> GRANDE GOIÂNIA | AC8152: =TEXT(G8152,"dd/mm/aaaa") -> 13/01/2026
A8153: ord6yjqov | B8153: 2026-01-07 09:48:44 | C8153: Amanda Aparecida da Silva lima | D8153: (12) 98294-5137 | F8153: 321.833.378-42 | G8153: 2026-01-13 16:31:31 | H8153: 197 | I8153: Dinheiro | M8153: São José dos Campos | N8153: SP | O8153: Completo | S8153: Alan São paulo | W8153: Felipe alexandre De souza | AB8153: =_xlfn.XLOOKUP(S8153,contatos_gerentes!D:D,contatos_gerentes!B:B) -> GRANDE SÃO PAULO | AC8153: =TEXT(G8153,"dd/mm/aaaa") -> 13/01/2026
A8154: ordqgozm2 | B8154: 2026-01-07 10:12:39 | C8154: Elza Maria Rocha | D8154: (37) 99106-9769 | F8154: 412.394.580-53 | G8154: 2026-01-14 10:22:37 | H8154: 97 | I8154: Cartão de Débito | M8154: Nova Serrana | N8154: MG | O8154: Completo | S8154: Tiago Belo horizonte | W8154: Lucimar José martins | AB8154: =_xlfn.XLOOKUP(S8154,contatos_gerentes!D:D,contatos_gerentes!B:B) -> GRANDE BELO HORIZONTE | AC8154: =TEXT(G8154,"dd/mm/aaaa") -> 14/01/2026
A8155: orddxe69m/ordk2p67y | B8155: 2026-01-07 12:04:31 | C8155: Roselene Martins (esposo vai receber) | D8155: (11) 95140-9670 | F8155: 329.109.458-12 | G8155: 2026-01-12 11:09:31 | H8155: 167 | I8155: Cartão de Crédito | M8155: Franco da Rocha | N8155: SP | O8155: Completo | S8155: Alan São paulo | W8155: Leonardo Andrade nascimento antônio | AB8155: =_xlfn.XLOOKUP(S8155,contatos_gerentes!D:D,contatos_gerentes!B:B) -> GRANDE SÃO PAULO | AC8155: =TEXT(G8155,"dd/mm/aaaa") -> 12/01/2026
... A8158: ordz7l2qy | B8158: 2026-01-07 13:33:06 | C8158: Maria Madalena Domingos | D8158: (41) 99828-7582 | F8158: 387.697.808-46 | G8158: 2026-01-12 12:15:35 | H8158: 139.99 | I8158: Dinheiro | M8158: Fazenda Rio Grande | N8158: PR | O8158: Completo | S8158: Gidalto Curitiba | W8158: Felipe Rodrigues | AB8158: =_xlfn.XLOOKUP(S8158,contatos_gerentes!D:D,contatos_gerentes!B:B) -> GRANDE CURITIBA | AC8158: =TEXT(G8158,"dd/mm/aaaa") -> 12/01/2026
A8159: ord9pmgpn | B8159: 2026-01-07 14:13:26 | C8159: Cloris C meurer Brito | D8159: (47) 99666-6159 | F8159: 082.795.643-65 | G8159: 2026-01-12 17:08:26 | H8159: 147 | I8159: Cartão de Crédito | M8159: Jaraguá do Sul | N8159: SC | O8159: Completo | S8159: Matheus Navegantes | W8159: Bruno Augustinho matias | AB8159: GRANDE NAVEGANTES | AC8159: =TEXT(G8159,"dd/mm/aaaa") -> 12/01/2026
A8160: ordz7lyyr | B8160: 2026-01-07 14:54:17 | C8160: CELINA MARIA DE MENDONCA | D8160: (37) 98815-5225 | F8160: 507.271.256-72 | G8160: 2026-01-14 17:23:27 | H8160: 139.99 | I8160: Cartão de Débito | M8160: Divinópolis | N8160: MG | O8160: Completo | S8160: Tiago Belo horizonte | W8160: Bruno Martins | AB8160: =_xlfn.XLOOKUP(S8160,contatos_gerentes!D:D,contatos_gerentes!B:B) -> GRANDE BELO HORIZONTE | AC8160: =TEXT(G8160,"dd/mm/aaaa") -> 14/01/2026
A8161: ord39yp5r | B8161: 2026-01-07 16:08:25 | C8161: Luiza Alves | D8161: (41) 99145-0502 | F8161: 037.271.243-69 | G8161: 2026-01-12 16:22:45 | H8161: 139.99 | I8161: Dinheiro | M8161: Curitiba | N8161: PR | O8161: Completo | S8161: Gidalto Curitiba | W8161: João Paulo de lima | AB8161: =_xlfn.XLOOKUP(S8161,contatos_gerentes!D:D,contatos_gerentes!B:B) -> GRANDE CURITIBA | AC8161: =TEXT(G8161,"dd/mm/aaaa") -> 12/01/2026
A8162: ordgdpg56 | B8162: 2026-01-07 17:14:17 | C8162: Luiz Trevisan | D8162: (15) 99146-3512 | F8162: 211.051.972-04 | G8162: 2026-01-12 10:27:44 | H8162: 100 | I8162: Dinheiro | M8162: Campo Limpo Paulista | N8162: SP | O8162: Completo | S8162: Alan São paulo | W8162: Maicon Da silva rocha | AB8162: =_xlfn.XLOOKUP(S8162,contatos_gerentes!D:D,contatos_gerentes!B:B) -> GRANDE SÃO PAULO | AC8162: =TEXT(G8162,"dd/mm/aaaa") -> 12/01/2026
A8163: ordjx70kx | B8163: 2026-01-07 17:22:07 | C8163: Giselle de Castro Vilela | D8163: (61) 99147-2399 | F8163: 025.299.572-40 | G8163: 2026-01-13 14:39:55 | H8163: 297 | I8163: PIX | M8163: Brasília | N8163: DF | O8163: Completo | S8163: Adriel Goiânia | W8163: Daniel Tiago das merces silva | AB8163: =_xlfn.XLOOKUP(S8163,contatos_gerentes!D:D,contatos_gerentes!B:B) -> GRANDE GOIÂNIA | AC8163: =TEXT(G8163,"dd/mm/aaaa") -> 13/01/2026
A8164: ordm27gg3 | B8164: 2026-01-07 17:45:42 | C8164: maria aparecida | D8164: (11) 97517-4089 | F8164: 520.533.598-03 | G8164: 2026-01-12 10:59:45 | H8164: 139.9 | I8164: Dinheiro | M8164: Campo Limpo Paulista | N8164: SP | O8164: Completo | S8164: Alan São paulo | W8164: Maicon Da silva rocha | AB8164: =_xlfn.XLOOKUP(S8164,contatos_gerentes!D:D,contatos_gerentes!B:B) -> GRANDE SÃO PAULO | AC8164: =TEXT(G8164,"dd/mm/aaaa") -> 12/01/2026
A8165: ordvq2ez3 | B8165: 2026-01-07 18:09:14 | C8165: Anderson Finger | D8165: (54) 99127-9850 | F8165: 352.394.419-87 | G8165: 2026-01-13 14:08:30 | H8165: 164.99 | I8165: PIX | M8165: Caxias do Sul | N8165: RS | O8165: Completo | S8165: Darlan Porto alegre | W8165: Luiz Felipe valin caetano | AB8165: =_xlfn.XLOOKUP(S8165,contatos_gerentes!D:D,contatos_gerentes!B:B) -> GRANDE PORTO ALEGRE | AC8165: =TEXT(G8165,"dd/mm/aaaa") -> 13/01/2026
A8166: ordgdp03e | B8166: 2026-01-07 19:10:04 | C8166: José Roberto | D8166: (13) 99632-7777 | F8166: 361.967.208-30 | G8166: 2026-01-14 15:51:21 | H8166: 147 | I8166: Cartão de Débito | M8166: Santos | N8166: SP | O8166: Completo | S8166: Alan São paulo | W8166: Mateus Brasil silva | AB8166: =_xlfn.XLOOKUP(S8166,contatos_gerentes!D:D,contatos_gerentes!B:B) -> GRANDE SÃO PAULO | AC8166: =TEXT(G8166,"dd/mm/aaaa") -> 14/01/2026
A8167: ordz7lkzy | B8167: 2026-01-07 19:33:31 | C8167: Cleusa de Oliveira Barbosa | D8167: (51) 99530-6141 | F8167: 001.154.316-75 | G8167: 2026-01-12 14:52:36 | H8167: 139.99 | I8167: Cartão de Débito | M8167: Portão | N8167: RS | O8167: Completo | S8167: Darlan Porto alegre | W8167: Leomar Horbach vieira | AB8167: =_xlfn.XLOOKUP(S8167,contatos_gerentes!D:D,contatos_gerentes!B:B) -> GRANDE PORTO ALEGRE | AC8167: =TEXT(G8167,"dd/mm/aaaa") -> 12/01/2026
A8168: orddxe02k | B8168: 2026-01-07 19:44:41 | C8168: Bernadete Liduario | D8168: (37) 98829-1981 | F8168: 077.249.576-90 | G8168: 2026-01-14 15:33:39 | H8168: 119 | I8168: Cartão de Débito | M8168: Divinópolis | N8168: MG | O8168: Completo | S8168: Tiago Belo horizonte | W8168: Lucimar José martins | AB8168: =_xlfn.XLOOKUP(S8168,contatos_gerentes!D:D,contatos_gerentes!B:B) -> GRANDE BELO HORIZONTE | AC8168: =TEXT(G8168,"dd/mm/aaaa") -> 14/01/2026
A8169: ord9pmj0o | B8169: 2026-01-07 19:58:09 | C8169: Rosa Cristina | D8169: (92) 99145-6701 | F8169: 472.454.763-49 | G8169: 2026-01-13 13:27:41 | H8169: 297 | I8169: Cartão de Débito | M8169: Manaus | N8169: AM | O8169: Completo | S8169: Giselle Manaus | W8169: Robson Pimentel barros | AB8169: =_xlfn.XLOOKUP(S8169,contatos_gerentes!D:D,contatos_gerentes!B:B) -> GRANDE MANAUS | AC8169: =TEXT(G8169,"dd/mm/aaaa") -> 13/01/2026
A8170: ord7om9d9 | B8170: 2026-01-07 20:12:55 | C8170: Elenice Carvalho | D8170: (61) 99685-2367 | F8170: 442.167.771-04 | G8170: 2026-01-13 12:33:08 | H8170: 150 | I8170: Cartão de Crédito | M8170: Brasília | N8170: DF | O8170: Completo | S8170: Adriel Goiânia | W8170: Leonardo Cunha lima | AB8170: =_xlfn.XLOOKUP(S8170,contatos_gerentes!D:D,contatos_gerentes!B:B) -> GRANDE GOIÂNIA | AC8170: =TEXT(G8170,"dd/mm/aaaa") -> 13/01/2026
A8171: ord0le6pm | B8171: 2026-01-07 21:41:04 | C8171: Maristela Bosqueiro Pansera | D8171: (54) 99631-1840 | F8171: 681.843.010-49 | G8171: 2026-01-13 08:54:14 | H8171: 297 | I8171: Cartão de Crédito | M8171: Farroupilha | N8171: RS | O8171: Completo | S8171: Darlan Porto alegre | W8171: Leomar Horbach vieira | AB8171: =_xlfn.XLOOKUP(S8171,contatos_gerentes!D:D,contatos_gerentes!B:B) -> GRANDE PORTO ALEGRE | AC8171: =TEXT(G8171,"dd/mm/aaaa") -> 13/01/2026
A8172: ordqgojq2 | B8172: 2026-01-07 21:47:21 | C8172: Ana Paula Micelli | D8172: (11) 99495-9454 | F8172: 104.049.837-07 | G8172: 2026-01-14 16:05:50 | H8172: 179 | I8172: Pix | M8172: Santos | N8172: SP | O8172: Completo | S8172: Alan São paulo | W8172: Mateus Brasil silva | AB8172: =_xlfn.XLOOKUP(S8172,contatos_gerentes!D:D,contatos_gerentes!B:B) -> GRANDE SÃO PAULO | AC8172: =TEXT(G8172,"dd/mm/aaaa") -> 14/01/2026
A8173: ordz7lkq6 | B8173: 2026-01-07 22:01:22 | C8173: Walquiria Cristina | D8173: (91) 98199-1645 | F8173: 169.691.382-91 | G8173: 2026-01-12 10:39:03 | H8173: 119 | I8173: PIX | M8173: Belém | N8173: PA | O8173: Completo | S8173: Michely vilhena Kikuchi | W8173: Leandro Robson da silva carneiro | AB8173: GRANDE BELÉM | AC8173: =TEXT(G8173,"dd/mm/aaaa") -> 12/01/2026
A8174: ordvq267m | B8174: 2026-01-07 22:15:10 | C8174: Elenilda a | D8174: (13) 99781-3842 | F8174: 385.559.228-44 | G8174: 2026-01-14 12:49:37 | H8174: 677 | I8174: Cartão de Débito | M8174: Santos | N8174: SP | O8174: Completo | S8174: Alan São paulo | W8174: Mateus Brasil silva | AB8174: =_xlfn.XLOOKUP(S8174,contatos_gerentes!D:D,contatos_gerentes!B:B) -> GRANDE SÃO PAULO | AC8174: =TEXT(G8174,"dd/mm/aaaa") -> 14/01/2026
A8175: ordrjypoe | B8175: 2026-01-07 22:29:48 | C8175: Adriana Marques de Souza | D8175: (11) 94797-4239 | F8175: 173.388.928-06 | G8175: 2026-01-12 11:21:34 | H8175: 197 | I8175: PIX | M8175: Itaquaquecetuba | N8175: SP | O8175: Completo | S8175: Alan São paulo | W8175: Willian vinicius Marques de oliveira | AB8175: =_xlfn.XLOOKUP(S8175,contatos_gerentes!D:D,contatos_gerentes!B:B) -> GRANDE SÃO PAULO | AC8175: =TEXT(G8175,"dd/mm/aaaa") -> 12/01/2026
A8176: ordy75onj | B8176: 2026-01-08 00:45:42 | C8176: Virginia . | D8176: (31) 98265-8072 | F8176: 154.797.089-88 | G8176: 2026-01-12 11:19:00 | H8176: 189.9 | I8176: Dinheiro | M8176: Belo Horizonte | N8176: MG | O8176: Completo | S8176: Tiago Belo horizonte | W8176: Wallace Lucas monteiro de castro | AB8176: =_xlfn.XLOOKUP(S8176,contatos_gerentes!D:D,contatos_gerentes!B:B) -> GRANDE BELO HORIZONTE | AC8176: =TEXT(G8176,"dd/mm/aaaa") -> 12/01/2026
A8177: ord5oj3dl | B8177: 2026-01-08 02:03:05 | C8177: Ivonea Ramires Pozzan | D8177: (51) 98490-9171 | F8177: 521.540.250-72 | G8177: 2026-01-12 13:46:43 | H8177: 297.9 | I8177: Dinheiro | M8177: Porto Alegre | N8177: RS | O8177: Completo | S8177: Darlan Porto alegre | W8177: Carlos samuel Cardoso garcia | AB8177: =_xlfn.XLOOKUP(S8177,contatos_gerentes!D:D,contatos_gerentes!B:B) -> GRANDE PORTO ALEGRE | AC8177: =TEXT(G8177,"dd/mm/aaaa") -> 12/01/2026
A8178: ordlo7xyd | B8178: 2026-01-08 06:18:18 | C8178: Maria Celia lima calçada silva | D8178: (11) 98691-3667 | F8178: 250.578.548-10 | G8178: 2026-01-12 12:06:20 | H8178: 297 | I8178: Cartão de Débito | M8178: São Paulo | N8178: SP | O8178: Completo | S8178: Alan São paulo | W8178: Eduardo De oliveira figueiredo | AB8178: =_xlfn.XLOOKUP(S8178,contatos_gerentes!D:D,contatos_gerentes!B:B) -> GRANDE SÃO PAULO | AC8178: =TEXT(G8178,"dd/mm/aaaa") -> 12/01/2026
A8179: ord2gn3gv | B8179: 2026-01-08 07:59:08 | C8179: Jose Antonio Ferreira Da Silva | D8179: (31) 99070-0102 | F8179: 026.281.301-73 | G8179: 2026-01-12 10:54:02 | H8179: 170 | I8179: Dinheiro | M8179: Belo Horizonte | N8179: MG | O8179: Completo | S8179: Tiago Belo horizonte | W8179: Felipe dos santos Martins rodrigues | AB8179: =_xlfn.XLOOKUP(S8179,contatos_gerentes!D:D,contatos_gerentes!B:B) -> GRANDE BELO HORIZONTE | AC8179: =TEXT(G8179,"dd/mm/aaaa") -> 12/01/2026
A8180: ordk2pjpm/ord1gy3y0 | B8180: 2026-01-08 08:39:25 | C8180: Claucielia Alves Ribeiro | D8180: (62) 99146-4364 | F8180: 004.251.631-56 | G8180: 2026-01-12 12:43:29 | H8180: 177.9 | I8180: Cartão de Débito | M8180: Goiânia | N8180: GO | O8180: Completo | S8180: Adriel Goiânia | W8180: Adriano De almeida silva | AB8180: =_xlfn.XLOOKUP(S8180,contatos_gerentes!D:D,contatos_gerentes!B:B) -> GRANDE GOIÂNIA | AC8180: =TEXT(G8180,"dd/mm/aaaa") -> 12/01/2026
A8181: ordp9j6k2 | B8181: 2026-01-08 08:43:55 | C8181: Lucinei Alves da Silva | D8181: (11) 97704-2960 | F8181: 113.696.978-05 | G8181: 2026-01-12 08:27:43 | H8181: 189.9 | I8181: Cartão de Crédito | M8181: Osasco | N8181: SP | O8181: Completo | S8181: Alan São paulo | W8181: Paulo Cesar dos santos | AB8181: =_xlfn.XLOOKUP(S8181,contatos_gerentes!D:D,contatos_gerentes!B:B) -> GRANDE SÃO PAULO | AC8181: =TEXT(G8181,"dd/mm/aaaa") -> 12/01/2026
A8182: ordlo7x3o | B8182: 2026-01-08 08:45:30 | C8182: Maridalva S Paiva | D8182: (11) 96130-3459 | F8182: 156.621.258-80 | G8182: 2026-01-12 09:10:12 | H8182: 99.9 | I8182: Cartão de Débito | M8182: São Paulo | N8182: SP | O8182: Completo | S8182: Alan São paulo | W8182: Plinio Renan correa do prado | AB8182: =_xlfn.XLOOKUP(S8182,contatos_gerentes!D:D,contatos_gerentes!B:B) -> GRANDE SÃO PAULO | AC8182: =TEXT(G8182,"dd/mm/aaaa") -> 12/01/2026
A8183: ordvq21d2 | B8183: 2026-01-08 08:49:01 | C8183: Silvana Arcoverde | D8183: (81) 99707-0155 | F8183: 459.300.404-78 | G8183: 2026-01-12 16:01:34 | H8183: 197 | I8183: Cartão de Crédito | M8183: Recife | N8183: PE | O8183: Completo | S8183: Aaron Recife | W8183: Anderson Santos de freitas | AB8183: =_xlfn.XLOOKUP(S8183,contatos_gerentes!D:D,contatos_gerentes!B:B) -> GRANDE RECIFE | AC8183: =TEXT(G8183,"dd/mm/aaaa") -> 12/01/2026
A8184: ordn9pmq3 | B8184: 2026-01-08 08:50:00 | C8184: Bernadette Liduario | D8184: (37) 98829-1981 | F8184: 119.347.546-50 | G8184: 2026-01-14 15:34:38 | H8184: 159.99 | I8184: Cartão de Débito | M8184: Divinópolis | N8184: MG | O8184: Completo | S8184: Tiago Belo horizonte | W8184: Lucimar José martins | AB8184: =_xlfn.XLOOKUP(S8184,contatos_gerentes!D:D,contatos_gerentes!B:B) -> GRANDE BELO HORIZONTE | AC8184: =TEXT(G8184,"dd/mm/aaaa") -> 14/01/2026
A8185: ordo6oldg | B8185: 2026-01-08 09:02:18 | C8185: Lourival Antonio Costa | D8185: (37) 99965-9881 | F8185: 219.219.706-34 | G8185: 2026-01-14 15:02:59 | H8185: 99.99 | I8185: Cartão de Débito | M8185: Divinópolis | N8185: MG | O8185: Completo | S8185: Tiago Belo horizonte | W8185: Lucimar José martins | AB8185: =_xlfn.XLOOKUP(S8185,contatos_gerentes!D:D,contatos_gerentes!B:B) -> GRANDE BELO HORIZONTE | AC8185: =TEXT(G8185,"dd/mm/aaaa") -> 14/01/2026
... A8191: ordm27513 | B8191: 2026-01-08 10:01:17 | C8191: Franci Maia | D8191: (92) 92665-6979 | F8191: 124.604.838-80 | G8191: 2026-01-12 13:49:57 | H8191: 99.9 | I8191: Cartão de Débito | M8191: Manaus | N8191: AM | O8191: Completo | S8191: Giselle Manaus | W8191: Robson Pimentel barros | AB8191: =_xlfn.XLOOKUP(S8191,contatos_gerentes!D:D,contatos_gerentes!B:B) -> GRANDE MANAUS | AC8191: =TEXT(G8191,"dd/mm/aaaa") -> 12/01/2026
A8192: ordlo7xxe | B8192: 2026-01-08 10:08:16 | C8192: Janete SC | D8192: (47) 99726-9991 | F8192: 220.476.976-20 | G8192: 2026-01-13 11:52:00 | H8192: 150 | I8192: PIX | M8192: Joinville | N8192: SC | O8192: Completo | S8192: Matheus Navegantes | W8192: Bruno Augustinho matias | AB8192: GRANDE NAVEGANTES | AC8192: =TEXT(G8192,"dd/mm/aaaa") -> 13/01/2026
A8193: ordvq2116 | B8193: 2026-01-08 10:08:34 | C8193: Rose Mica Petit | D8193: (54) 98156-6307 | F8193: 036.999.061-75 | G8193: 2026-01-13 12:43:53 | H8193: 119.9 | I8193: PIX | M8193: Caxias do Sul | N8193: RS | O8193: Completo | S8193: Darlan Porto alegre | W8193: Leomar Horbach vieira | AB8193: =_xlfn.XLOOKUP(S8193,contatos_gerentes!D:D,contatos_gerentes!B:B) -> GRANDE PORTO ALEGRE | AC8193: =TEXT(G8193,"dd/mm/aaaa") -> 13/01/2026
...

Sheet contatos_gerentes
A1: NOME DO GERENTE | B1: OPERAÇÃO | C1: WHATSAPP | D1: operador
A2: Gidalto Dos santos | B2: GRANDE CURITIBA | C2: 41 92005-7292 | D2: Gidalto Curitiba
A3: Juliana Fischer | B3: GRANDE RIO DE JANEIRO | C3: 21 99855-9043 | D3: Juliana Rj
A4: Aaron Lucena mendes | B4: GRANDE RECIFE | C4: 81 9575-6143 | D4: Aaron Recife
A5: Tiago Belo horizonte | B5: GRANDE BELO HORIZONTE | C5: 31 9313-4107 | D5: Tiago Belo horizonte
A6: Alan Hideki | B6: GRANDE SÃO PAULO | C6: 11 99189-9831 | D6: Alan São paulo
A7: Juliana Montezuma ellery | B7: GRANDE FORTALEZA | C7: 85 8960-0500 | D7: Juliana Fortaleza
A8: Thiago Batista | B8: GRANDE TERESINA | C8: 86 9998-0359 | D8: Thiago Teresina
A9: Darlan Rodrigues | B9: GRANDE PORTO ALEGRE | C9: 51 9800-5264 | D9: Darlan Porto alegre
A10: Franklin Torres | B10: GRANDE SÃO LUIS | C10: 98 8338-9137 | D10: Franklin São luis
A11: Angel Duarte ribeiro | B11: GRANDE NATAL | C11: 84 9827-7171 | D11: Angel Natal
A12: Roseneide Soares da silva | B12: GRANDE SALVADOR | C12: 71 8730-9506 | D12: Roseneide Salvador
... A17: Fuad Campo grande | B17: GRANDE CAMPO GRANDE | C17: 67 96542111 | D17: Fuad Campo grande
A18: Lucelia De fatima silva | B18: GRANDE JOÃO PESSOA | C18: 83 8105-4433 | D18: #N/A
A19: Matheus Navegantes | B19: GRANDE NAVEGANTES | C19: 43 9952-0929 | D19: Matheus Navegantes
A20: Michely vilhena Kikuchi | B20: GRANDE BELÉM | C20: 91 8536-3030 | D20: Michely vilhena Kikuchi

Sheet excluir_entregadores
A1: Nome do entregador
A2: Rafael Munhoz teste
A3: Rafael Teste 2
A4: Rafael Teste 3
A5: Vinícius Teste
A6: Vinicius Teste
A7: Anthony De frança santiago
A8: Edva Karlla chaves queiroz
A9: Giovanni Candido calcagnit
A10: Deivid Venceslau caze
A11: Victor Hugo da cruz alves
A12: Felipe alexandre De souza
... A25: Joao Vitor ferraz santos
